pinjected_wandb/__init__.py
pinjected_wandb/artifact_util.py
pinjected_wandb-0.1.2.dist-info/METADATA
pinjected_wandb-0.1.2.dist-info/WHEEL
pinjected_wandb-0.1.2.dist-info/RECORD
